README.md
setup.py
neural_renderer/__init__.py
neural_renderer/get_points_from_angles.py
neural_renderer/lighting.py
neural_renderer/load_obj.py
neural_renderer/look.py
neural_renderer/look_at.py
neural_renderer/mesh.py
neural_renderer/perspective.py
neural_renderer/projection.py
neural_renderer/rasterize.py
neural_renderer/renderer.py
neural_renderer/save_obj.py
neural_renderer/vertices_to_faces.py
neural_renderer/cuda/__init__.py
neural_renderer/cuda/create_texture_image_cuda.cpp
neural_renderer/cuda/create_texture_image_cuda_kernel.cu
neural_renderer/cuda/load_textures_cuda.cpp
neural_renderer/cuda/load_textures_cuda_kernel.cu
neural_renderer/cuda/rasterize_cuda.cpp
neural_renderer/cuda/rasterize_cuda_kernel.cu
neural_renderer_pytorch.egg-info/PKG-INFO
neural_renderer_pytorch.egg-info/SOURCES.txt
neural_renderer_pytorch.egg-info/dependency_links.txt
neural_renderer_pytorch.egg-info/requires.txt
neural_renderer_pytorch.egg-info/top_level.txt